SPI/DD_PUF_STIMULI/controller_dd.v
`timescale 1ns/1ps
`define RESET_CONDITION 0

module controller_dd(
    input [7:0] CODE,
    input [15:0] CNT_VAL,
    input RESET,
    input CLK,
    input [127:0] PUF_OUT,
    output reg RESET_DD,
	output reg START_DD,
    output reg DONE,
    output reg [127:0] PUF_OUT_REG
);

localparam [3:0] 
    RESET_STATE   = 4'd0,
    IDLE_STATE    = 4'd1,
    START_STATE  = 4'd2,
    SAMPLE_STATE  = 4'd3,
    WAIT_STATE    = 4'd4;

reg [15:0] CNT;
reg [15:0] CNT_REG;
reg [2:0] PRS, NES;
wire TRIG_SIG = (CODE == 8'd1); // Trigger when CODE == 1

// State machine (Sequential logic)
always @(posedge CLK or posedge RESET) begin
    if (RESET == `RESET_CONDITION) 
        PRS <= RESET_STATE;
    else
        PRS <= NES;
end

// Output and internal signal assignments (Combinational logic)
always @(posedge CLK) begin
    if (RESET == `RESET_CONDITION) begin
        CNT      = 16'd0;
        CNT_REG  = 16'd1;
        RESET_DD = 1'b1;
        START_DD    = 1'b0;
        DONE      = 1'b0;
        PUF_OUT_REG = 128'd0;
    end else begin
        case (PRS)
            RESET_STATE: begin
                CNT      = 16'd0;
                CNT_REG  = 16'd1;
                RESET_DD = 1'b1;
				START_DD    = 1'b0;
				DONE      = 1'b0;
				PUF_OUT_REG = 128'd0;
            end

            IDLE_STATE: begin
                CNT      = 16'd0;
                CNT_REG  = CNT_VAL;
                RESET_DD = 1'b1;
				START_DD    = 1'b0;
                DONE      = 1'b0;
                PUF_OUT_REG = PUF_OUT_REG;
            end

            START_STATE: begin
                CNT      = CNT+1;
                CNT_REG  = CNT_VAL;
                RESET_DD = 1'b0;
				START_DD    = 1'b1;
                DONE      = 1'b0;
                PUF_OUT_REG = PUF_OUT_REG;
            end

            SAMPLE_STATE: begin
                CNT      = 16'd0;
                CNT_REG  = CNT_VAL;
                RESET_DD = 1'b0;
				START_DD    = 1'b1;
                DONE      = 1'b1;
                PUF_OUT_REG = PUF_OUT;
            end

            WAIT_STATE: begin
                CNT      = 16'd0;
                CNT_REG  = CNT_REG;
                RESET_DD = 1'b1;
				START_DD    = 1'b0;
                DONE      = 1'b0;
                PUF_OUT_REG = PUF_OUT_REG;
            end

            default: begin
                CNT      = 16'd0;
                CNT_REG  = 16'd1;
                RESET_DD = 1'b1;
				START_DD    = 1'b0;
				DONE      = 1'b0;
				PUF_OUT_REG = 128'd0;
            end
        endcase
    end
end

// State decision logic (Sequential logic)
always @(*) begin
    if (RESET == `RESET_CONDITION)
        NES <= RESET_STATE;
    else begin
        case (PRS)
            RESET_STATE:
                NES <= IDLE_STATE;

            IDLE_STATE: begin
                if (TRIG_SIG == 0)
                    NES <= IDLE_STATE;
                else
                    NES <= START_STATE;
            end

            START_STATE: begin
                if (CNT < CNT_REG)
                    NES <= START_STATE;
                else
                    NES <= SAMPLE_STATE;
            end

            SAMPLE_STATE: 
                NES <= WAIT_STATE;

            WAIT_STATE: begin
                if (TRIG_SIG == 0)
                    NES <= IDLE_STATE;
                else
                    NES <= WAIT_STATE;
            end
            default:
                NES <= RESET_STATE;
        endcase
    end
end

endmodule

SPI/DD_PUF_STIMULI/tb_controller.v
`timescale 1ns/1ps
`include "./controller_dd.v"
module tb_controller_dd;

  // Parameter for clock period
  parameter CLK_PERIOD = 10;  // Default clock period is 10ns (you can change this)

  // Declare inputs as regs and outputs as wires
  reg [7:0] CODE;
  reg [15:0] CNT_VAL;
  reg RESET;
  reg CLK;
  reg [127:0] PUF_OUT;
  
  wire RESET_DD;
  wire START_DD;
  wire DONE;
  wire [127:0] PUF_OUT_REG;

  // Instantiate the controller_xor module
  controller_dd uut (
    .CODE(CODE),
    .CNT_VAL(CNT_VAL),
    .RESET(RESET),
    .CLK(CLK),
    .PUF_OUT(PUF_OUT),
    .RESET_DD(RESET_DD),
    .START_DD(START_DD),
    .DONE(DONE),
    .PUF_OUT_REG(PUF_OUT_REG)
  );

  // Clock generation (use CLK_PERIOD as the clock period)
  always begin
    #(CLK_PERIOD / 2) CLK = ~CLK; // Toggle the clock every half period
  end

  // Initial block to apply stimulus
  initial begin
    $dumpfile("waveform.vcd");  // File name for the VCD dump
    $dumpvars(0, tb_controller_dd);     // Dump all signals in the testbench
    // Initialize signals
    CLK = 0;
    RESET = 0;  // Apply reset initially
    CODE = 8'd0;
    CNT_VAL = 16'd10;
    PUF_OUT = 128'hA5A5A5A5A5A5A5A5A5A5A5A5A5A5A5A5;  // Arbitrary value for PUF_OUT
    #(CLK_PERIOD)

    RESET = 1; 
    CODE = 8'd0;
    #(CLK_PERIOD)
    CODE = 8'd1;
    #(CNT_VAL*CLK_PERIOD);
    // Set up VCD file for waveform generation
    CODE = 8'd4;
    #(10*CLK_PERIOD)
    $finish;
  end


endmodule

SPI/DD_PUF_STIMULI/waveform.vcd
$date
	Thu Nov  7 19:27:00 2024
$end
$version
	Icarus Verilog
$end
$timescale
	1ps
$end
$scope module tb_controller_dd $end
$var wire 1 ! START_DD $end
$var wire 1 " RESET_DD $end
$var wire 128 # PUF_OUT_REG [127:0] $end
$var wire 1 $ DONE $end
$var parameter 32 % CLK_PERIOD $end
$var reg 1 & CLK $end
$var reg 16 ' CNT_VAL [15:0] $end
$var reg 8 ( CODE [7:0] $end
$var reg 128 ) PUF_OUT [127:0] $end
$var reg 1 * RESET $end
$scope module uut $end
$var wire 1 & CLK $end
$var wire 16 + CNT_VAL [15:0] $end
$var wire 8 , CODE [7:0] $end
$var wire 128 - PUF_OUT [127:0] $end
$var wire 1 * RESET $end
$var wire 1 . TRIG_SIG $end
$var parameter 4 / IDLE_STATE $end
$var parameter 4 0 RESET_STATE $end
$var parameter 4 1 SAMPLE_STATE $end
$var parameter 4 2 START_STATE $end
$var parameter 4 3 WAIT_STATE $end
$var reg 16 4 CNT [15:0] $end
$var reg 16 5 CNT_REG [15:0] $end
$var reg 1 $ DONE $end
$var reg 3 6 NES [2:0] $end
$var reg 3 7 PRS [2:0] $end
$var reg 128 8 PUF_OUT_REG [127:0] $end
$var reg 1 " RESET_DD $end
$var reg 1 ! START_DD $end
$upscope $end
$upscope $end
$enddefinitions $end
$comment Show the parameter values. $end
$dumpall
b100 3
b10 2
b11 1
b0 0
b1 /
b1010 %
$end
#0
$dumpvars
bx 8
bx 7
b0 6
bx 5
bx 4
0.
b10100101101001011010010110100101101001011010010110100101101001011010010110100101101001011010010110100101101001011010010110100101 -
b0 ,
b1010 +
0*
b10100101101001011010010110100101101001011010010110100101101001011010010110100101101001011010010110100101101001011010010110100101 )
b0 (
b1010 '
0&
x$
bx #
x"
x!
$end
#5000
b0 7
b0 #
b0 8
0$
0!
1"
b1 5
b0 4
1&
#10000
b1 6
0&
1*
#15000
b1 7
1&
#20000
b10 6
0&
1.
b1 (
b1 ,
#25000
b10 7
b1010 5
1&
#30000
0&
#35000
1!
0"
b1 4
1&
#40000
0&
#45000
b10 4
1&
#50000
0&
#55000
b11 4
1&
#60000
0&
#65000
b100 4
1&
#70000
0&
#75000
b101 4
1&
#80000
0&
#85000
b110 4
1&
#90000
0&
#95000
b111 4
1&
#100000
0&
#105000
b1000 4
1&
#110000
0&
#115000
b1001 4
1&
#120000
0&
0.
b100 (
b100 ,
#125000
b11 6
b1010 4
1&
#130000
0&
#135000
b100 6
b11 7
b1011 4
1&
#140000
0&
#145000
b1 6
b100 7
b10100101101001011010010110100101101001011010010110100101101001011010010110100101101001011010010110100101101001011010010110100101 #
b10100101101001011010010110100101101001011010010110100101101001011010010110100101101001011010010110100101101001011010010110100101 8
1$
b0 4
1&
#150000
0&
#155000
b1 7
0$
0!
1"
1&
