SPI/SPI_MACRO/SPI.v
`timescale 1ns / 1ps
//(*KEEP_HIERARCHY="YES"*)
module SPI
	#(
		parameter LENGTH=136,
		parameter RCOND=0
	)
	(
		input MOSI,
		input SCK,
		input CLK,
		input SSEL,
		input RESET,
		input [LENGTH-1:0]TO_SEND,
		output reg [LENGTH-1:0]RECEIVED,
		output reg RXED,
		output reg TXED,
		output reg MISO
    );

(*ASYNC_REG="TRUE"*)
reg [1:0] B_MOSI;
(*ASYNC_REG="TRUE"*)
reg [1:0] B_SSEL;
(*ASYNC_REG="TRUE"*)
reg [1:0]B_SCK;

reg [1:0] PRS, NES; //present and next state of the machine
reg [LENGTH-1:0]B_RECEIVED; //shift register to store MOSI data 
reg [8:0]CNT; //counter of the machine
localparam [1:0] //states of FSM
	ZERO=2'b00,
	ONE=2'b01,
	TWO=2'b10;


wire PE_SCK,NE_SCK,PE_SSEL,NE_SSEL;

assign PE_SCK=(B_SCK===(2'b01));//capture the rising edge
assign NE_SCK=(B_SCK===(2'b10));//capture the falling edge

//interface to ft232h CDC
always @(posedge CLK)
begin
	if(RESET==RCOND)
	begin
		B_SCK<=2'b00;
		B_SSEL<=2'b00;
		B_MOSI<=2'b00;
	end
	else
	begin
		B_SCK<={B_SCK[0],SCK};
		B_SSEL<={B_SSEL[0],SSEL};
		B_MOSI<={B_MOSI[0],MOSI};
	end
end

always @(posedge CLK)
begin
	if(RESET==RCOND)
		PRS<=ZERO;
	else
		PRS<=NES;	
end

always @(*)
begin
	NES<=ZERO;
	begin
		case(PRS)
			ZERO:
			begin
				if(!B_SSEL[1])
					NES<=ONE;
				else
					NES<=ZERO;
			end
			ONE:
			begin
				if(CNT==LENGTH)//CHECK THIS
					NES<=TWO;
				else
					NES<=ONE;
			end
			TWO:
			begin
				if(B_SSEL[1])
				begin
					NES<=ZERO;
				end
				else
					NES<=TWO;
			end
			default:
				NES<=ZERO;
		endcase
	end
end

//OUTPUT LOGIC
always @(posedge CLK)
begin
	if(RESET==RCOND)
	begin
		RXED<=0;
		TXED<=0;
		RECEIVED<={LENGTH{1'b0}};
		B_RECEIVED<={LENGTH{1'b0}};		
		MISO<=1'bZ;
		CNT<=0;
	end
	else
	begin
		case(PRS)
			ZERO:
			begin
				CNT<=0;
				RXED<=0;
				TXED<=0;
				B_RECEIVED<={LENGTH{1'b0}};
				MISO<=1'bZ;
			end
			ONE:
			begin
				if(CNT<LENGTH)
				begin
					MISO<=TO_SEND[LENGTH-1-CNT];
					if (PE_SCK)
					begin
						B_RECEIVED<={B_RECEIVED[LENGTH-1-1:0],B_MOSI[1]};					
					end
					else if(NE_SCK)		
					begin			
						CNT<=CNT+1'b1;	
						if(CNT+1<LENGTH)
							MISO<=TO_SEND[LENGTH-2-CNT];
						else
							MISO<=TO_SEND[0];
					end
				end
				else
					MISO<=TO_SEND[0];
			end
			TWO:
			begin
				MISO<=TO_SEND[0];
				CNT<=0;
				RXED<=1;
				TXED<=1;
				RECEIVED<=B_RECEIVED;
			end
			default:
			begin
				MISO<=1'bZ;
				CNT<=0;
				RXED<=0;
				TXED<=0;
				B_RECEIVED<={LENGTH{1'b0}};
				RECEIVED<={LENGTH{1'b0}};
			end
	endcase
	end
end
endmodule

SPI/SPI_MACRO/TB.v
`timescale 1ns / 1ps
`define MY_LENGTH 64

module TB;

	// Inputs
	reg MOSI;
	reg SCK;
	reg CLK_50;
	reg SSEL;
	reg RESET;
	reg [`MY_LENGTH-1:0] TO_SEND;

	// Outputs
	wire [`MY_LENGTH-1:0] RECEIVED;
	wire RXED;
	wire TXED;
	wire MISO;

	// Instantiate the Unit Under Test (UUT)
	SPI #(.LENGTH(`MY_LENGTH))uut (
		.MOSI(MOSI), 
		.SCK(SCK), 
		.CLK(CLK_50), 
		.SSEL(SSEL), 
		.RESET(RESET), 
		.TO_SEND(TO_SEND), 
		.RECEIVED(RECEIVED), 
		.RXED(RXED), 
		.TXED(TXED), 
		.MISO(MISO)
	);
	
	reg [`MY_LENGTH-1:0] TRANSMITTED;

	initial begin
		// Initialize Inputs
        $dumpfile("waveform.vcd");
        $dumpvars();
		MOSI = 0;
		TRANSMITTED = {`MY_LENGTH{1'b0}};
		SCK = 0;
		CLK_50 = 0;
		SSEL = 1;
		RESET = 1;
		TO_SEND = {$random,$random,$random,$random,$random,$random,$random,$random};
		#100;
		RESET = 0;
		#100;
		RESET = 1;
		// Wait 100 ns for global reset to finish
		#100;
		msend(TO_SEND);
		#1000;
      $stop;

	end

	//generate the 50 MHz clock:
	localparam period50=20; //1/(20 ns)=50MHz	
	always
	begin
		#(period50/2) CLK_50=1;
		#(period50/2) CLK_50=0;
	end
	
	//value for 12 MHz
	localparam period12=83.3; //	1/(83.3 ns)=12MHz
	

	//FUNCTIONS (TASKS) THAT I HAVE USED IN THE PROCEDURAL CODE
	
	//procedure to receive a message
   task msend(input [`MY_LENGTH-1:0]TOSEND);
		localparam period12=83.3;
		integer j;
		begin		
			for(j=0;j<`MY_LENGTH;j=j+1)
				begin
					SSEL = 0;
					#1;
					MOSI = TOSEND[`MY_LENGTH-1-j];
					#(period12/20);
					SCK = 1;
					#(period12/2);
					SCK=0;
					TRANSMITTED<={TRANSMITTED[`MY_LENGTH-1-1:0],MISO};					
					#(9*period12/20);
				end
			if(TRANSMITTED==TO_SEND)
				$display("trasmissione avvenuta con successo");
			else
				$display("errore in trasmissione");
			#100;
			SSEL = 1;
			if (uut.RECEIVED==TOSEND)
				$display("ricezione avvenuta correttamente");
			#100;
		end
	endtask
	
	
endmodule

SPI/SPI_MACRO/waveform.vcd
$date
	Tue Nov 12 15:02:35 2024
$end
$version
	Icarus Verilog
$end
$timescale
	1ps
$end
$scope module TB $end
$var wire 1 ! TXED $end
$var wire 1 " RXED $end
$var wire 64 # RECEIVED [63:0] $end
$var wire 1 $ MISO $end
$var real 1 % period12 $end
$var parameter 32 & period50 $end
$var reg 1 ' CLK_50 $end
$var reg 1 ( MOSI $end
$var reg 1 ) RESET $end
$var reg 1 * SCK $end
$var reg 1 + SSEL $end
$var reg 64 , TO_SEND [63:0] $end
$var reg 64 - TRANSMITTED [63:0] $end
$scope module uut $end
$var wire 1 ' CLK $end
$var wire 1 ( MOSI $end
$var wire 1 ) RESET $end
$var wire 1 * SCK $end
$var wire 1 + SSEL $end
$var wire 64 . TO_SEND [63:0] $end
$var wire 1 / PE_SCK $end
$var wire 1 0 NE_SCK $end
$var parameter 32 1 LENGTH $end
$var parameter 2 2 ONE $end
$var parameter 32 3 RCOND $end
$var parameter 2 4 TWO $end
$var parameter 2 5 ZERO $end
$var reg 2 6 B_MOSI [1:0] $end
$var reg 64 7 B_RECEIVED [63:0] $end
$var reg 2 8 B_SCK [1:0] $end
$var reg 2 9 B_SSEL [1:0] $end
$var reg 9 : CNT [8:0] $end
$var reg 1 $ MISO $end
$var reg 2 ; NES [1:0] $end
$var reg 2 < PRS [1:0] $end
$var reg 64 = RECEIVED [63:0] $end
$var reg 1 " RXED $end
$var reg 1 ! TXED $end
$upscope $end
$scope task msend $end
$var real 1 > period12 $end
$var reg 64 ? TOSEND [63:0] $end
$var integer 32 @ j [31:0] $end
$upscope $end
$upscope $end
$enddefinitions $end
$comment Show the parameter values. $end
$dumpall
r83.3 >
b0 5
b10 4
b0 3
b1 2
b1000000 1
b10100 &
r83.3 %
$end
#0
$dumpvars
bx @
bx ?
bx =
bx <
bx ;
bx :
bx 9
bx 8
bx 7
bx 6
00
0/
b1011001011000010100001000110010110001001001101110101001000010010 .
b0 -
b1011001011000010100001000110010110001001001101110101001000010010 ,
1+
0*
1)
0(
0'
x$
bx #
x"
x!
$end
#10000
b0 ;
bx0 6
bx1 9
bx0 8
b0 #
b0 =
b0 7
0!
0"
b0 :
z$
1'
#20000
0'
#30000
b0 <
b0 6
b11 9
b0 8
1'
#40000
0'
#50000
1'
#60000
0'
#70000
1'
#80000
0'
#90000
1'
#100000
0'
0)
#110000
b1 ;
b0 9
1'
#120000
0'
#130000
1'
#140000
0'
#150000
1'
#160000
0'
#170000
1'
#180000
0'
#190000
1'
#200000
0'
1)
#210000
b1 ;
b1 9
b1 <
1'
#220000
0'
#230000
b1 ;
1$
b11 9
1'
#240000
0'
#250000
1'
#260000
0'
#270000
1'
#280000
0'
#290000
1'
#300000
0'
0+
b0 @
b1011001011000010100001000110010110001001001101110101001000010010 ?
#301000
1(
#305165
1*
#310000
b1 ;
b1 6
b10 9
1/
b1 8
1'
#320000
0'
#330000
b1 ;
b11 6
b0 9
0/
b11 8
1'
#340000
0'
#346815
b1 -
0*
#350000
10
b10 8
1'
#360000
0'
#370000
b1 ;
00
b0 8
b1 :
1'
#380000
0'
#384300
b1 @
#385300
0(
#389465
1*
#390000
0$
b10 6
1/
b1 8
1'
#400000
0'
#410000
b0 6
0/
b11 8
b1 7
1'
#420000
0'
#430000
1'
#431115
b10 -
0*
#440000
0'
#450000
10
b10 8
1'
#460000
0'
#468600
b10 @
#469600
1(
#470000
b1 ;
b10 :
b1 6
00
b0 8
1'
#473765
1*
#480000
0'
#490000
b11 6
1/
b1 8
1$
1'
#500000
0'
#510000
b11 7
0/
b11 8
1'
#515415
b101 -
0*
#520000
0'
#530000
10
b10 8
1'
#540000
0'
#550000
b1 ;
b11 :
00
b0 8
1'
#552900
b11 @
#558065
1*
#560000
0'
#570000
1/
b1 8
1'
#580000
0'
#590000
b111 7
0/
b11 8
1'
#599715
b1011 -
0*
#600000
0'
#610000
10
b10 8
1'
#620000
0'
#630000
b1 ;
b100 :
00
b0 8
1'
#637200
b100 @
#638200
0(
#640000
0'
#642365
1*
#650000
b10 6
1/
b1 8
0$
1'
#660000
0'
#670000
b1111 7
b0 6
0/
b11 8
1'
#680000
0'
#684015
b10110 -
0*
#690000
10
b10 8
1'
#700000
0'
#710000
b1 ;
b101 :
00
b0 8
1'
#720000
0'
#721500
b101 @
#726665
1*
#730000
1/
b1 8
1'
#740000
0'
#750000
b11110 7
0/
b11 8
1'
#760000
0'
#768315
b101100 -
0*
#770000
10
b10 8
1'
#780000
0'
#790000
b1 ;
b110 :
00
b0 8
1'
#800000
0'
#805800
b110 @
#806800
1(
#810000
b1 6
1$
1'
#810965
1*
#820000
0'
#830000
b11 6
1/
b1 8
1'
#840000
0'
#850000
0/
b11 8
b111101 7
1'
#852615
b1011001 -
0*
#860000
0'
#870000
10
b10 8
1'
#880000
0'
#890000
b1 ;
00
b0 8
b111 :
1'
#890100
b111 @
#891100
0(
#895265
1*
#900000
0'
#910000
0$
b10 6
1/
b1 8
1'
#920000
0'
#930000
b0 6
0/
b11 8
b1111011 7
1'
#936915
b10110010 -
0*
#940000
0'
#950000
10
b10 8
1'
#960000
0'
#970000
b1 ;
00
b0 8
b1000 :
1'
#974400
b1000 @
#975400
1(
#979565
1*
#980000
0'
#990000
1$
b1 6
1/
b1 8
1'
#1000000
0'
#1010000
b11 6
0/
b11 8
b11110110 7
1'
#1020000
0'
#1021215
b101100101 -
0*
#1030000
10
b10 8
1'
#1040000
0'
#1050000
b1 ;
00
b0 8
b1001 :
1'
#1058700
b1001 @
#1060000
0'
#1063865
1*
#1070000
1/
b1 8
1'
#1080000
0'
#1090000
0/
b11 8
b111101101 7
1'
#1100000
0'
#1105515
b1011001011 -
0*
#1110000
10
b10 8
1'
#1120000
0'
#1130000
b1 ;
00
b0 8
b1010 :
1'
#1140000
0'
#1143000
b1010 @
#1144000
0(
#1148165
1*
#1150000
0$
b10 6
1/
b1 8
1'
#1160000
0'
#1170000
b0 6
0/
b11 8
b1111011011 7
1'
#1180000
0'
#1189815
b10110010110 -
0*
#1190000
10
b10 8
1'
#1200000
0'
#1210000
b1 ;
00
b0 8
b1011 :
1'
#1220000
0'
#1227300
b1011 @
#1230000
1'
#1232465
1*
#1240000
0'
#1250000
1/
b1 8
1'
#1260000
0'
#1270000
b11110110110 7
0/
b11 8
1'
#1274115
b101100101100 -
0*
#1280000
0'
#1290000
10
b10 8
1'
#1300000
0'
#1310000
b1 ;
b1100 :
00
b0 8
1'
#1311600
b1100 @
#1316765
1*
#1320000
0'
#1330000
1/
b1 8
1'
#1340000
0'
#1350000
b111101101100 7
0/
b11 8
1'
#1358415
b1011001011000 -
0*
#1360000
0'
#1370000
10
b10 8
1'
#1380000
0'
#1390000
b1 ;
b1101 :
00
b0 8
1'
#1395900
b1101 @
#1400000
0'
#1401065
1*
#1410000
1/
b1 8
1'
#1420000
0'
#1430000
b1111011011000 7
0/
b11 8
1'
#1440000
0'
#1442715
b10110010110000 -
0*
#1450000
10
b10 8
1'
#1460000
0'
#1470000
b1 ;
b1110 :
00
b0 8
1'
#1480000
0'
#1480200
b1110 @
#1481200
1(
#1485365
1*
#1490000
b1 6
1/
b1 8
1$
1'
#1500000
0'
#1510000
b11110110110000 7
b11 6
0/
b11 8
1'
#1520000
0'
#1527015
b101100101100001 -
0*
#1530000
10
b10 8
1'
#1540000
0'
#1550000
b1 ;
b1111 :
00
b0 8
1'
#1560000
0'
#1564500
b1111 @
#1565500
0(
#1569665
1*
#1570000
b10 6
1/
b1 8
0$
1'
#1580000
0'
#1590000
b111101101100001 7
b0 6
0/
b11 8
1'
#1600000
0'
#1610000
1'
#1611315
b1011001011000010 -
0*
#1620000
0'
#1630000
10
b10 8
1'
#1640000
0'
#1648800
b10000 @
#1649800
1(
#1650000
b1 ;
b1 6
00
b0 8
b10000 :
1'
#1653965
1*
#1660000
0'
#1670000
1$
b11 6
1/
b1 8
1'
#1680000
0'
#1690000
0/
b11 8
b1111011011000011 7
1'
#1695615
b10110010110000101 -
0*
#1700000
0'
#1710000
10
b10 8
1'
#1720000
0'
#1730000
b1 ;
00
b0 8
b10001 :
1'
#1733100
b10001 @
#1734100
0(
#1738265
1*
#1740000
0'
#1750000
0$
b10 6
1/
b1 8
1'
#1760000
0'
#1770000
b0 6
0/
b11 8
b11110110110000111 7
1'
#1779915
b101100101100001010 -
0*
#1780000
0'
#1790000
10
b10 8
1'
#1800000
0'
#1810000
b1 ;
00
b0 8
b10010 :
1'
#1817400
b10010 @
#1820000
0'
#1822565
1*
#1830000
1/
b1 8
1'
#1840000
0'
#1850000
0/
b11 8
b111101101100001110 7
1'
#1860000
0'
#1864215
b1011001011000010100 -
0*
#1870000
10
b10 8
1'
#1880000
0'
#1890000
b1 ;
00
b0 8
b10011 :
1'
#1900000
0'
#1901700
b10011 @
#1906865
1*
#1910000
1/
b1 8
1'
#1920000
0'
#1930000
0/
b11 8
b1111011011000011100 7
1'
#1940000
0'
#1948515
b10110010110000101000 -
0*
#1950000
10
b10 8
1'
#1960000
0'
#1970000
b1 ;
00
b0 8
b10100 :
1'
#1980000
0'
#1986000
b10100 @
#1990000
1'
#1991165
1*
#2000000
0'
#2010000
1/
b1 8
1'
#2020000
0'
#2030000
b11110110110000111000 7
0/
b11 8
1'
#2032815
b101100101100001010000 -
0*
#2040000
0'
#2050000
10
b10 8
1'
#2060000
0'
#2070000
b1 ;
b10101 :
00
b0 8
1'
#2070300
b10101 @
#2071300
1(
#2075465
1*
#2080000
0'
#2090000
b1 6
1/
b1 8
1$
1'
#2100000
0'
#2110000
b111101101100001110000 7
b11 6
0/
b11 8
1'
#2117115
b1011001011000010100001 -
0*
#2120000
0'
#2130000
10
b10 8
1'
#2140000
0'
#2150000
b1 ;
b10110 :
00
b0 8
1'
#2154600
b10110 @
#2155600
0(
#2159765
1*
#2160000
0'
#2170000
b10 6
1/
b1 8
0$
1'
#2180000
0'
#2190000
b1111011011000011100001 7
b0 6
0/
b11 8
1'
#2200000
0'
#2201415
b10110010110000101000010 -
0*
#2210000
10
b10 8
1'
#2220000
0'
#2230000
b1 ;
b10111 :
00
b0 8
1'
#2238900
b10111 @
#2240000
0'
#2244065
1*
#2250000
1/
b1 8
1'
#2260000
0'
#2270000
b11110110110000111000010 7
0/
b11 8
1'
#2280000
0'
#2285715
b101100101100001010000100 -
0*
#2290000
10
b10 8
1'
#2300000
0'
#2310000
b1 ;
b11000 :
00
b0 8
1'
#2320000
0'
#2323200
b11000 @
#2328365
1*
#2330000
1/
b1 8
1'
#2340000
0'
#2350000
b111101101100001110000100 7
0/
b11 8
1'
#2360000
0'
#2370000
1'
#2370015
b1011001011000010100001000 -
0*
#2380000
0'
#2390000
10
b10 8
1'
#2400000
0'
#2407500
b11001 @
#2408500
1(
#2410000
b1 ;
b1 6
00
b0 8
b11001 :
1'
#2412665
1*
#2420000
0'
#2430000
1$
b11 6
1/
b1 8
1'
#2440000
0'
#2450000
0/
b11 8
b1111011011000011100001001 7
1'
#2454315
b10110010110000101000010001 -
0*
#2460000
0'
#2470000
10
b10 8
1'
#2480000
0'
#2490000
b1 ;
00
b0 8
b11010 :
1'
#2491800
b11010 @
#2496965
1*
#2500000
0'
#2510000
1/
b1 8
1'
#2520000
0'
#2530000
0/
b11 8
b11110110110000111000010011 7
1'
#2538615
b101100101100001010000100011 -
0*
#2540000
0'
#2550000
10
b10 8
1'
#2560000
0'
#2570000
b1 ;
00
b0 8
b11011 :
1'
#2576100
b11011 @
#2577100
0(
#2580000
0'
#2581265
1*
#2590000
0$
b10 6
1/
b1 8
1'
#2600000
0'
#2610000
b0 6
0/
b11 8
b111101101100001110000100111 7
1'
#2620000
0'
#2622915
b1011001011000010100001000110 -
0*
#2630000
10
b10 8
1'
#2640000
0'
#2650000
b1 ;
00
b0 8
b11100 :
1'
#2660000
0'
#2660400
b11100 @
#2665565
1*
#2670000
1/
b1 8
1'
#2680000
0'
#2690000
0/
b11 8
b1111011011000011100001001110 7
1'
#2700000
0'
#2707215
b10110010110000101000010001100 -
0*
#2710000
10
b10 8
1'
#2720000
0'
#2730000
b1 ;
00
b0 8
b11101 :
1'
#2740000
0'
#2744700
b11101 @
#2745700
1(
#2749865
1*
#2750000
1$
b1 6
1/
b1 8
1'
#2760000
0'
#2770000
b11 6
0/
b11 8
b11110110110000111000010011100 7
1'
#2780000
0'
#2790000
1'
#2791515
b101100101100001010000100011001 -
0*
#2800000
0'
#2810000
10
b10 8
1'
#2820000
0'
#2829000
b11110 @
#2830000
b1 ;
b11110 :
b10 6
00
b0 8
0(
1'
#2834165
1*
#2840000
0'
#2850000
b0 6
1/
b1 8
0$
1'
#2860000
0'
#2870000
b111101101100001110000100111000 7
0/
b11 8
1'
#2875815
b1011001011000010100001000110010 -
0*
#2880000
0'
#2890000
10
b10 8
1'
#2900000
0'
#2910000
b1 ;
b11111 :
00
b0 8
1'
#2913300
b11111 @
#2914300
1(
#2918465
1*
#2920000
0'
#2930000
b1 6
1/
b1 8
1$
1'
#2940000
0'
#2950000
b1111011011000011100001001110000 7
b11 6
0/
b11 8
1'
#2960000
0'
#2960115
b10110010110000101000010001100101 -
0*
#2970000
10
b10 8
1'
#2980000
0'
#2990000
b1 ;
b100000 :
00
b0 8
1'
#2997600
b100000 @
#3000000
0'
#3002765
1*
#3010000
1/
b1 8
1'
#3020000
0'
#3030000
b11110110110000111000010011100001 7
0/
b11 8
1'
#3040000
0'
#3044415
b101100101100001010000100011001011 -
0*
#3050000
10
b10 8
1'
#3060000
0'
#3070000
b1 ;
b100001 :
00
b0 8
1'
#3080000
0'
#3081900
b100001 @
#3082900
0(
#3087065
1*
#3090000
b10 6
1/
b1 8
0$
1'
#3100000
0'
#3110000
b111101101100001110000100111000011 7
b0 6
0/
b11 8
1'
#3120000
0'
#3128715
b1011001011000010100001000110010110 -
0*
#3130000
10
b10 8
1'
#3140000
0'
#3150000
b1 ;
b100010 :
00
b0 8
1'
#3160000
0'
#3166200
b100010 @
#3170000
1'
#3171365
1*
#3180000
0'
#3190000
1/
b1 8
1'
#3200000
0'
#3210000
0/
b11 8
b1111011011000011100001001110000110 7
1'
#3213015
b10110010110000101000010001100101100 -
0*
#3220000
0'
#3230000
10
b10 8
1'
#3240000
0'
#3250000
b1 ;
00
b0 8
b100011 :
1'
#3250500
b100011 @
#3255665
1*
#3260000
0'
#3270000
1/
b1 8
1'
#3280000
0'
#3290000
0/
b11 8
b11110110110000111000010011100001100 7
1'
#3297315
b101100101100001010000100011001011000 -
0*
#3300000
0'
#3310000
10
b10 8
1'
#3320000
0'
#3330000
b1 ;
00
b0 8
b100100 :
1'
#3334800
b100100 @
#3335800
1(
#3339965
1*
#3340000
0'
#3350000
1$
b1 6
1/
b1 8
1'
#3360000
0'
#3370000
b11 6
0/
b11 8
b111101101100001110000100111000011000 7
1'
#3380000
0'
#3381615
b1011001011000010100001000110010110001 -
0*
#3390000
10
b10 8
1'
#3400000
0'
#3410000
b1 ;
00
b0 8
b100101 :
1'
#3419100
b100101 @
#3420000
0'
#3420100
0(
#3424265
1*
#3430000
0$
b10 6
1/
b1 8
1'
#3440000
0'
#3450000
b0 6
0/
b11 8
b1111011011000011100001001110000110001 7
1'
#3460000
0'
#3465915
b10110010110000101000010001100101100010 -
0*
#3470000
10
b10 8
1'
#3480000
0'
#3490000
b1 ;
00
b0 8
b100110 :
1'
#3500000
0'
#3503400
b100110 @
#3508565
1*
#3510000
1/
b1 8
1'
#3520000
0'
#3530000
0/
b11 8
b11110110110000111000010011100001100010 7
1'
#3540000
0'
#3550000
1'
#3550215
b101100101100001010000100011001011000100 -
0*
#3560000
0'
#3570000
10
b10 8
1'
#3580000
0'
#3587700
b100111 @
#3588700
1(
#3590000
b1 ;
b100111 :
b1 6
00
b0 8
1'
#3592865
1*
#3600000
0'
#3610000
b11 6
1/
b1 8
1$
1'
#3620000
0'
#3630000
b111101101100001110000100111000011000101 7
0/
b11 8
1'
#3634515
b1011001011000010100001000110010110001001 -
0*
#3640000
0'
#3650000
10
b10 8
1'
#3660000
0'
#3670000
b1 ;
b101000 :
00
b0 8
1'
#3672000
b101000 @
#3673000
0(
#3677165
1*
#3680000
0'
#3690000
b10 6
1/
b1 8
0$
1'
#3700000
0'
#3710000
b1111011011000011100001001110000110001011 7
b0 6
0/
b11 8
1'
#3718815
b10110010110000101000010001100101100010010 -
0*
#3720000
0'
#3730000
10
b10 8
1'
#3740000
0'
#3750000
b1 ;
b101001 :
00
b0 8
1'
#3756300
b101001 @
#3760000
0'
#3761465
1*
#3770000
1/
b1 8
1'
#3780000
0'
#3790000
b11110110110000111000010011100001100010110 7
0/
b11 8
1'
#3800000
0'
#3803115
b101100101100001010000100011001011000100100 -
0*
#3810000
10
b10 8
1'
#3820000
0'
#3830000
b1 ;
b101010 :
00
b0 8
1'
#3840000
0'
#3840600
b101010 @
#3841600
1(
#3845765
1*
#3850000
b1 6
1/
b1 8
1$
1'
#3860000
0'
#3870000
b111101101100001110000100111000011000101100 7
b11 6
0/
b11 8
1'
#3880000
0'
#3887415
b1011001011000010100001000110010110001001001 -
0*
#3890000
10
b10 8
1'
#3900000
0'
#3910000
b1 ;
b101011 :
00
b0 8
1'
#3920000
0'
#3924900
b101011 @
#3930000
1'
#3930065
1*
#3940000
0'
#3950000
1/
b1 8
1'
#3960000
0'
#3970000
0/
b11 8
b1111011011000011100001001110000110001011001 7
1'
#3971715
b10110010110000101000010001100101100010010011 -
0*
#3980000
0'
#3990000
10
b10 8
1'
#4000000
0'
#4009200
b101100 @
#4010000
b1 ;
00
b0 8
b101100 :
1'
#4010200
0(
#4014365
1*
#4020000
0'
#4030000
0$
b10 6
1/
b1 8
1'
#4040000
0'
#4050000
b0 6
0/
b11 8
b11110110110000111000010011100001100010110011 7
1'
#4056015
b101100101100001010000100011001011000100100110 -
0*
#4060000
0'
#4070000
10
b10 8
1'
#4080000
0'
#4090000
b1 ;
00
b0 8
b101101 :
1'
#4093500
b101101 @
#4094500
1(
#4098665
1*
#4100000
0'
#4110000
1$
b1 6
1/
b1 8
1'
#4120000
0'
#4130000
b11 6
0/
b11 8
b111101101100001110000100111000011000101100110 7
1'
#4140000
0'
#4140315
b1011001011000010100001000110010110001001001101 -
0*
#4150000
10
b10 8
1'
#4160000
0'
#4170000
b1 ;
00
b0 8
b101110 :
1'
#4177800
b101110 @
#4180000
0'
#4182965
1*
#4190000
1/
b1 8
1'
#4200000
0'
#4210000
0/
b11 8
b1111011011000011100001001110000110001011001101 7
1'
#4220000
0'
#4224615
b10110010110000101000010001100101100010010011011 -
0*
#4230000
10
b10 8
1'
#4240000
0'
#4250000
b1 ;
00
b0 8
b101111 :
1'
#4260000
0'
#4262100
b101111 @
#4267265
1*
#4270000
1/
b1 8
1'
#4280000
0'
#4290000
0/
b11 8
b11110110110000111000010011100001100010110011011 7
1'
#4300000
0'
#4308915
b101100101100001010000100011001011000100100110111 -
0*
#4310000
10
b10 8
1'
#4320000
0'
#4330000
b1 ;
00
b0 8
b110000 :
1'
#4340000
0'
#4346400
b110000 @
#4347400
0(
#4350000
0$
b10 6
1'
#4351565
1*
#4360000
0'
#4370000
b0 6
1/
b1 8
1'
#4380000
0'
#4390000
b111101101100001110000100111000011000101100110110 7
0/
b11 8
1'
#4393215
b1011001011000010100001000110010110001001001101110 -
0*
#4400000
0'
#4410000
10
b10 8
1'
#4420000
0'
#4430000
b1 ;
b110001 :
00
b0 8
1'
#4430700
b110001 @
#4431700
1(
#4435865
1*
#4440000
0'
#4450000
b1 6
1/
b1 8
1$
1'
#4460000
0'
#4470000
b1111011011000011100001001110000110001011001101100 7
b11 6
0/
b11 8
1'
#4477515
b10110010110000101000010001100101100010010011011101 -
0*
#4480000
0'
#4490000
10
b10 8
1'
#4500000
0'
#4510000
b1 ;
b110010 :
00
b0 8
1'
#4515000
b110010 @
#4516000
0(
#4520000
0'
#4520165
1*
#4530000
b10 6
1/
b1 8
0$
1'
#4540000
0'
#4550000
b11110110110000111000010011100001100010110011011001 7
b0 6
0/
b11 8
1'
#4560000
0'
#4561815
b101100101100001010000100011001011000100100110111010 -
0*
#4570000
10
b10 8
1'
#4580000
0'
#4590000
b1 ;
b110011 :
00
b0 8
1'
#4599300
b110011 @
#4600000
0'
#4600300
1(
#4604465
1*
#4610000
b1 6
1/
b1 8
1$
1'
#4620000
0'
#4630000
b111101101100001110000100111000011000101100110110010 7
b11 6
0/
b11 8
1'
#4640000
0'
#4646115
b1011001011000010100001000110010110001001001101110101 -
0*
#4650000
10
b10 8
1'
#4660000
0'
#4670000
b1 ;
b110100 :
00
b0 8
1'
#4680000
0'
#4683600
b110100 @
#4684600
0(
#4688765
1*
#4690000
b10 6
1/
b1 8
0$
1'
#4700000
0'
#4710000
b1111011011000011100001001110000110001011001101100101 7
b0 6
0/
b11 8
1'
#4720000
0'
#4730000
1'
#4730415
b10110010110000101000010001100101100010010011011101010 -
0*
#4740000
0'
#4750000
10
b10 8
1'
#4760000
0'
#4767900
b110101 @
#4770000
b1 ;
00
b0 8
b110101 :
1'
#4773065
1*
#4780000
0'
#4790000
1/
b1 8
1'
#4800000
0'
#4810000
0/
b11 8
b11110110110000111000010011100001100010110011011001010 7
1'
#4814715
b101100101100001010000100011001011000100100110111010100 -
0*
#4820000
0'
#4830000
10
b10 8
1'
#4840000
0'
#4850000
b1 ;
00
b0 8
b110110 :
1'
#4852200
b110110 @
#4853200
1(
#4857365
1*
#4860000
0'
#4870000
1$
b1 6
1/
b1 8
1'
#4880000
0'
#4890000
b11 6
0/
b11 8
b111101101100001110000100111000011000101100110110010100 7
1'
#4899015
b1011001011000010100001000110010110001001001101110101001 -
0*
#4900000
0'
#4910000
10
b10 8
1'
#4920000
0'
#4930000
b1 ;
00
b0 8
b110111 :
1'
#4936500
b110111 @
#4937500
0(
#4940000
0'
#4941665
1*
#4950000
0$
b10 6
1/
b1 8
1'
#4960000
0'
#4970000
b0 6
0/
b11 8
b1111011011000011100001001110000110001011001101100101001 7
1'
#4980000
0'
#4983315
b10110010110000101000010001100101100010010011011101010010 -
0*
#4990000
10
b10 8
1'
#5000000
0'
#5010000
b1 ;
00
b0 8
b111000 :
1'
#5020000
0'
#5020800
b111000 @
#5025965
1*
#5030000
1/
b1 8
1'
#5040000
0'
#5050000
0/
b11 8
b11110110110000111000010011100001100010110011011001010010 7
1'
#5060000
0'
#5067615
b101100101100001010000100011001011000100100110111010100100 -
0*
#5070000
10
b10 8
1'
#5080000
0'
#5090000
b1 ;
00
b0 8
b111001 :
1'
#5100000
0'
#5105100
b111001 @
#5110000
1'
#5110265
1*
#5120000
0'
#5130000
1/
b1 8
1'
#5140000
0'
#5150000
b111101101100001110000100111000011000101100110110010100100 7
0/
b11 8
1'
#5151915
b1011001011000010100001000110010110001001001101110101001000 -
0*
#5160000
0'
#5170000
10
b10 8
1'
#5180000
0'
#5189400
b111010 @
#5190000
b1 ;
b111010 :
00
b0 8
1'
#5194565
1*
#5200000
0'
#5210000
1/
b1 8
1'
#5220000
0'
#5230000
b1111011011000011100001001110000110001011001101100101001000 7
0/
b11 8
1'
#5236215
b10110010110000101000010001100101100010010011011101010010000 -
0*
#5240000
0'
#5250000
10
b10 8
1'
#5260000
0'
#5270000
b1 ;
b111011 :
00
b0 8
1'
#5273700
b111011 @
#5274700
1(
#5278865
1*
#5280000
0'
#5290000
b1 6
1/
b1 8
1$
1'
#5300000
0'
#5310000
b11110110110000111000010011100001100010110011011001010010000 7
b11 6
0/
b11 8
1'
#5320000
0'
#5320515
b101100101100001010000100011001011000100100110111010100100001 -
0*
#5330000
10
b10 8
1'
#5340000
0'
#5350000
b1 ;
b111100 :
00
b0 8
1'
#5358000
b111100 @
#5359000
0(
#5360000
0'
#5363165
1*
#5370000
b10 6
1/
b1 8
0$
1'
#5380000
0'
#5390000
b111101101100001110000100111000011000101100110110010100100001 7
b0 6
0/
b11 8
1'
#5400000
0'
#5404815
b1011001011000010100001000110010110001001001101110101001000010 -
0*
#5410000
10
b10 8
1'
#5420000
0'
#5430000
b1 ;
b111101 :
00
b0 8
1'
#5440000
0'
#5442300
b111101 @
#5447465
1*
#5450000
1/
b1 8
1'
#5460000
0'
