DIGITAL_CONTROLLER/CODE_CONTROL.v
/*
	RICCARDO DELLA SALA
	Sapienza University of Rome
*/

/*
    +----+------------------+-------------+
    | Bit |      Signal     | Description |
    +----+------------------+-------------+
    |  0  | OTA_LASCAS_en   | OTA LASCAS  |
    |  1  | OTA_D2S_ENH_en  | OTA D2S ENH |
    |  2  | OTA_TREE_en     | OTA TREE    |
    |  3  | OTA_DIG_REZA_en | OTA DIG REZA|
    |  4  | OTA_GAIN_BOOST_ | Gain Boost  |
    |  5  | COMP_JLPEA_en   | COMP JLPEA  |
    |  6  | COMP_ACCESS_en  | COMP ACCESS |
    |  7  | LDO_en          | LDO enable  |
    |  8  | 1nA_LDO_en      | LDO 1nA     |
    |  9  | 10nA_LDO_en     | LDO 10nA    |
    | 10  | 100nA_LDO_en    | LDO 100nA   |
    | 11  | 250nA_LDO_en    | LDO 250nA   |
    | 12  | 500nA_LDO_en    | LDO 500nA   |
    | 13  | 750nA_LDO_en    | LDO 750nA   |
    | 14  | 1uA_LDO_en      | LDO 1uA     |
    | 15  | GND             | Ground      |
    +----+------------------+-------------+
*/

/* 
  Bit layout for 16-bit output:  
    15  14  13  12  11  10   9   8   7   6   5   4   3   2   1   0
*/
module demux_16bit (
    input [3:0] sel,           // 4-bit selection signal
    output reg [15:0] out      // 16-bit output based on selected register
);
    
    always @(*) begin
        // Default the output to all zeroes
        out = 16'b0;

        // Set the appropriate output pattern based on the selection input
        case (sel)
            4'b0000: out = 16'b0000000000000000;  // All powered off (GND)
            4'b0001: out = 16'b0000000000000001;  // OTA_LASCAS_en
            4'b0010: out = 16'b0000000000000010;  // OTA_D2S_ENH_en
            4'b0011: out = 16'b0000000000000100;  // OTA_TREE_en
            4'b0100: out = 16'b0000000000001000;  // OTA_DIG_REZA_en
            4'b0101: out = 16'b0000000000010000;  // OTA_GAIN_BOOSTING_en
            4'b0110: out = 16'b0000000000100000;  // COMP_JLPEA_en
            4'b0111: out = 16'b0000000001000000;  // COMP_ACCESS_en
            4'b1000: out = 16'b0000000010000000;  // LDO_en
            4'b1001: out = 16'b0000000110000000;  // 1nA_LDO_en
            4'b1010: out = 16'b0000001010000000;  // 10nA_LDO_en
            4'b1011: out = 16'b0000010010000000;  // 100nA_LDO_en
            4'b1100: out = 16'b0000100010000000;  // 250nA_LDO_en
            4'b1101: out = 16'b0001000010000000;  // 500nA_LDO_en
            4'b1110: out = 16'b0010000010000000;  // 750nA_LDO_en
            4'b1111: out = 16'b0100000010000000;  // 1uA_LDO_en
            default: out = 16'b0;                 // Default to zero for undefined cases
        endcase
    end
endmodule

DIGITAL_CONTROLLER/CODE_CONTROL_tb.v
module tb_demux_16bit;

    // Declare testbench signals
    reg [3:0] sel;          // 4-bit selection signal
    wire [15:0] out;        // 16-bit output

    // Instantiate the demux_16bit module
    demux_16bit uut (
        .sel(sel),           // Connect the selection signal
        .out(out)            // Connect the output wire
    );

    // Test sequence
    initial begin
        // Display the output for each selection
        $dumpfile("waveform.vcd");
        $dumpvars();
        $display("Testing Demux 16-bit Module...");
        $monitor("sel = %b, out = %b", sel, out);
        
        // Apply test vectors to sel
        sel = 4'b0000;  // Test: All powered off (GND)
        #10;            // Wait for 10 time units
        
        sel = 4'b0001;  // Test: OTA_LASCAS_en
        #10;
        
        sel = 4'b0010;  // Test: OTA_D2S_ENH_en
        #10;
        
        sel = 4'b0011;  // Test: OTA_TREE_en
        #10;
        
        sel = 4'b0100;  // Test: OTA_DIG_REZA_en
        #10;
        
        sel = 4'b0101;  // Test: OTA_GAIN_BOOSTING_en
        #10;
        
        sel = 4'b0110;  // Test: COMP_JLPEA_en
        #10;
        
        sel = 4'b0111;  // Test: COMP_ACCESS_en
        #10;
        
        sel = 4'b1000;  // Test: LDO_en
        #10;
        
        sel = 4'b1001;  // Test: 1nA_LDO_en
        #10;
        
        sel = 4'b1010;  // Test: 10nA_LDO_en
        #10;
        
        sel = 4'b1011;  // Test: 100nA_LDO_en
        #10;
        
        sel = 4'b1100;  // Test: 250nA_LDO_en
        #10;
        
        sel = 4'b1101;  // Test: 500nA_LDO_en
        #10;
        
        sel = 4'b1110;  // Test: 750nA_LDO_en
        #10;
        
        sel = 4'b1111;  // Test: 1uA_LDO_en
        #10;
        
        // Finish simulation
        $finish;
    end

    // Initialize signals
    initial begin
        sel = 4'b0000;  // Set initial value of sel
    end

endmodule

DIGITAL_CONTROLLER/dump.vcd
$date
	Wed Nov  6 13:15:29 2024
$end
$version
	Icarus Verilog
$end
$timescale
	1s
$end
$scope module tb_demux_16bit $end
$var wire 16 ! out [15:0] $end
$var reg 4 " sel [3:0] $end
$scope module uut $end
$var wire 4 # sel [3:0] $end
$var reg 16 $ out [15:0] $end
$upscope $end
$upscope $end
$enddefinitions $end
$comment Show the parameter values. $end
$dumpall
$end
#0
$dumpvars
b0 $
b0 #
b0 "
b0 !
$end
#10
b1 !
b1 $
b1 "
b1 #
#20
b10 !
b10 $
b10 "
b10 #
#30
b100 !
b100 $
b11 "
b11 #
#40
b1000 !
b1000 $
b100 "
b100 #
#50
b10000 !
b10000 $
b101 "
b101 #
#60
b100000 !
b100000 $
b110 "
b110 #
#70
b1000000 !
b1000000 $
b111 "
b111 #
#80
b10000000 !
b10000000 $
b1000 "
b1000 #
#90
b110000000 !
b110000000 $
b1001 "
b1001 #
#100
b1010000000 !
b1010000000 $
b1010 "
b1010 #
#110
b10010000000 !
b10010000000 $
b1011 "
b1011 #
#120
b100010000000 !
b100010000000 $
b1100 "
b1100 #
#130
b1000010000000 !
b1000010000000 $
b1101 "
b1101 #
#140
b10000010000000 !
b10000010000000 $
b1110 "
b1110 #
#150
b100000010000000 !
b100000010000000 $
b1111 "
b1111 #
